CHANGES.txt
CONTRIBUTORS.txt
MANIFEST.in
README.md
setup.py
docs/LICENSE.GPL
docs/LICENSE.txt
src/collective/__init__.py
src/collective.schedule.egg-info/PKG-INFO
src/collective.schedule.egg-info/SOURCES.txt
src/collective.schedule.egg-info/dependency_links.txt
src/collective.schedule.egg-info/entry_points.txt
src/collective.schedule.egg-info/namespace_packages.txt
src/collective.schedule.egg-info/not-zip-safe
src/collective.schedule.egg-info/pbr.json
src/collective.schedule.egg-info/requires.txt
src/collective.schedule.egg-info/top_level.txt
src/collective/schedule/__init__.py
src/collective/schedule/configure.zcml
src/collective/schedule/interfaces.py
src/collective/schedule/meta.py
src/collective/schedule/meta.zcml
src/collective/schedule/testing.py
src/collective/schedule/browser/__init__.py
src/collective/schedule/browser/configure.zcml
src/collective/schedule/browser/views.py
src/collective/schedule/tests/__init__.py
src/collective/schedule/tests/test_example.py
src/collective/schedule/tests/test_view.zcml
src/collective/schedule/tests/test_zcml.py