Metadata-Version: 1.1
Name: collective.schedule
Version: 0.2
Summary: Plone integration for the python 'schedule' library
Home-page: https://github.com/netsight/collective.schedule
Author: Matt Sital-Singh
Author-email: UNKNOWN
License: BSD
Keywords: python plone schedule cron
Platform: UNKNOWN
Classifier: Programming Language :: Python
